nasdaqdatalink/__init__.py
nasdaqdatalink/api_config.py
nasdaqdatalink/bulkdownload.py
nasdaqdatalink/connection.py
nasdaqdatalink/export_table.py
nasdaqdatalink/get.py
nasdaqdatalink/get_point_in_time.py
nasdaqdatalink/get_table.py
nasdaqdatalink/message.py
nasdaqdatalink/util.py
nasdaqdatalink/version.py
nasdaqdatalink/errors/__init__.py
nasdaqdatalink/errors/data_link_error.py
nasdaqdatalink/model/__init__.py
nasdaqdatalink/model/data.py
nasdaqdatalink/model/data_list.py
nasdaqdatalink/model/data_mixin.py
nasdaqdatalink/model/database.py
nasdaqdatalink/model/dataset.py
nasdaqdatalink/model/datatable.py
nasdaqdatalink/model/merged_data_list.py
nasdaqdatalink/model/merged_dataset.py
nasdaqdatalink/model/model_base.py
nasdaqdatalink/model/model_list.py
nasdaqdatalink/model/paginated_list.py
nasdaqdatalink/model/point_in_time.py
nasdaqdatalink/operations/__init__.py
nasdaqdatalink/operations/data_list.py
nasdaqdatalink/operations/get.py
nasdaqdatalink/operations/list.py
nasdaqdatalink/operations/operation.py
nasdaqdatalink/utils/__init__.py
nasdaqdatalink/utils/api_key_util.py
nasdaqdatalink/utils/request_type_util.py
Nasdaq_Data_Link-1.0.4.dist-info/LICENSE.txt
Nasdaq_Data_Link-1.0.4.dist-info/METADATA
Nasdaq_Data_Link-1.0.4.dist-info/WHEEL
Nasdaq_Data_Link-1.0.4.dist-info/top_level.txt
Nasdaq_Data_Link-1.0.4.dist-info/RECORD
