Metadata-Version: 2.1
Name: Nasdaq Data Link
Version: 1.0.4
Summary: Package for Nasdaq Data Link API access
Home-page: https://github.com/Nasdaq/data-link-python
Author: Nasdaq Data Link
Author-email: connect@data.nasdaq.com
Maintainer: Nasdaq Data Link Development Team
Maintainer-email: connect@data.nasdaq.com
License: MIT
Keywords: nasdaq data link,nasdaq,datalink,API,data,financial,economic
Platform: UNKNOWN
Classifier: Intended Audience :: Developers
Classifier: License :: OSI Approved :: MIT License
Classifier: Operating System :: OS Independent
Classifier: Programming Language :: Python :: 3.7
Classifier: Programming Language :: Python :: 3.8
Classifier: Programming Language :: Python :: 3.9
Classifier: Programming Language :: Python :: 3.10
Requires-Python: >= 3.7
License-File: LICENSE.txt
